[
  {
    "username": "system",
    "time": "2026-07-05T14:48:21.407Z",
    "ip": "221.13.89.138",
    "userAgent": "Mozilla/5.0 (Windows NT 10.0; Win64; x64) AppleWebKit/537.36 (KHTML, like Gecko) Chrome/150.0.0.0 Safari/537.36 Edg/150.0.0.0"
  },
  {
    "username": "yjp",
    "time": "2026-07-05T14:51:36.143Z",
    "ip": "221.13.89.138",
    "userAgent": "Mozilla/5.0 (Windows NT 10.0; Win64; x64) AppleWebKit/537.36 (KHTML, like Gecko) Chrome/150.0.0.0 Safari/537.36 Edg/150.0.0.0"
  },
  {
    "username": "ysm",
    "time": "2026-07-05T14:57:20.758Z",
    "ip": "221.13.89.138",
    "userAgent": "Mozilla/5.0 (Linux; Android 12; HarmonyOS; ADA-AL00; HMSCore 6.16.2.302) AppleWebKit/537.36 (KHTML, like Gecko) Chrome/99.0.4844.88 HuaweiBrowser/14.0.2.317 Mobile Safari/537.36"
  }
]